{
    "providers": {
        "awscloudformation": {
            "AuthRoleName": "livitysoundra-20190104144054-authRole",
            "UnauthRoleArn": "arn:aws:iam::972642169496:role/livitysoundra-20190104144054-unauthRole",
            "AuthRoleArn": "arn:aws:iam::972642169496:role/livitysoundra-20190104144054-authRole",
            "Region": "eu-west-1",
            "DeploymentBucketName": "livitysoundra-20190104144054-deployment",
            "UnauthRoleName": "livitysoundra-20190104144054-unauthRole",
            "StackName": "livitysoundra-20190104144054",
            "StackId": "arn:aws:cloudformation:eu-west-1:972642169496:stack/livitysoundra-20190104144054/be25f750-102e-11e9-b62d-0a4e84363f34"
        }
    },
    "api": {
        "livitysoundapi": {
            "service": "AppSync",
            "providerPlugin": "awscloudformation",
            "output": {
                "securityType": "API_KEY",
                "GraphQLAPIIdOutput": "wip5hkdhb5hf5c6wfzgxqnm4aa",
                "GraphQLAPIEndpointOutput": "https://eropmr6xmjenrbzi64p53q2pzq.appsync-api.eu-west-1.amazonaws.com/graphql",
                "GraphQLAPIKeyOutput": "da2-oeylcu5a55aufis5mwcubimhha"
            },
            "providerMetadata": {
                "s3TemplateURL": "https://s3.amazonaws.com/livitysoundra-20190104144054-deployment/amplify-cfn-templates/api/cloudformation-template.json",
                "logicalId": "apilivitysoundapi"
            },
            "lastPushTimeStamp": "2019-01-04T16:41:12.403Z",
            "lastPushDirHash": "8CfyLmiiRlBoDhrTc81HDLyOLAk="
        }
    },
    "auth": {
        "cognitobdceee6d": {
            "service": "Cognito",
            "providerPlugin": "awscloudformation",
            "providerMetadata": {
                "s3TemplateURL": "https://s3.amazonaws.com/livitysoundra-20190104144054-deployment/amplify-cfn-templates/auth/cognitobdceee6d-cloudformation-template.yml",
                "logicalId": "authcognitobdceee6d"
            },
            "lastPushTimeStamp": "2019-01-04T17:24:55.667Z",
            "output": {
                "IdentityPoolId": "eu-west-1:6302dc37-69d7-4ae2-9d17-230c12fd6f90",
                "IdentityPoolName": "livitysoundra_identitypool_61cb5757"
            },
            "lastPushDirHash": "QPPEwOR4FqL5g448TT8TZWpKsqo=",
            "[object Object]": {}
        }
    },
    "analytics": {
        "livitysoundra": {
            "service": "Pinpoint",
            "providerPlugin": "awscloudformation",
            "providerMetadata": {
                "s3TemplateURL": "https://s3.amazonaws.com/livitysoundra-20190104144054-deployment/amplify-cfn-templates/analytics/pinpoint-cloudformation-template.json",
                "logicalId": "analyticslivitysoundra"
            },
            "lastPushTimeStamp": "2019-01-04T16:41:11.261Z",
            "output": {
                "appName": "livitysoundra",
                "Region": "eu-west-1",
                "Id": "df0443df2f154a3aa6c418c8a44abf69"
            },
            "lastPushDirHash": "0VwigfIcLdzrGtHkCtqklz+M70g="
        }
    },
    "hosting": {
        "S3AndCloudFront": {
            "service": "S3AndCloudFront",
            "providerPlugin": "awscloudformation",
            "providerMetadata": {
                "s3TemplateURL": "https://s3.amazonaws.com/livitysoundra-20190104144054-deployment/amplify-cfn-templates/hosting/template.json",
                "logicalId": "hostingS3AndCloudFront"
            },
            "lastPushTimeStamp": "2019-01-04T16:41:11.267Z",
            "output": {
                "S3BucketSecureURL": "https://livitysoundra-20190104161948-hostingbucket.s3.amazonaws.com",
                "WebsiteURL": "http://livitysoundra-20190104161948-hostingbucket.s3-website-eu-west-1.amazonaws.com",
                "Region": "eu-west-1",
                "HostingBucketName": "livitysoundra-20190104161948-hostingbucket"
            },
            "lastPushDirHash": "uSRix9UG4wbBBiTxk6dcnRjq6Zo="
        }
    }
}